Proyecto/Unidad_Aritmetica/FA.vhd
library IEEE;
use IEEE.std_logic_1164.all;

 entity FA is
 
   port (a, b, cin: in std_logic;
         r, cout: out std_logic);
 end FA;
 
 architecture archFA of FA is
 begin
   cout <= (a and cin) or (a and b) or (b and cin);
   r <= (a xor (b xor cin));
 end archFA;

Proyecto/Unidad_Aritmetica/Sumador8Bits.vhd

library IEEE;
use IEEE.std_logic_1164.all;


 entity Sumador8Bits is
   port (A, B: in std_logic_vector (7 downto 0);
         cin: in std_logic;
         R: out std_logic_vector (7 downto 0); 
         cout: out std_logic;
         v: out std_logic);
 end Sumador8Bits;
 
 architecture archSumador of Sumador8Bits is
   component FA
     port (a, b, cin: in std_logic;
           r, cout: out std_logic);
   end component;

 signal C : std_logic_vector (6 downto 0);
 signal w : std_logic;

 begin
   Sumador0: FA port map (A(0), B(0), cin, R(0), C(0)); 
   Sumador1: FA port map (A(1), B(1), C(0), R(1), C(1)); 
   Sumador2: FA port map (A(2), B(2), C(1), R(2), C(2)); 
   Sumador3: FA port map (A(3), B(3), C(2), R(3), C(3)); 
   Sumador4: FA port map (A(4), B(4), C(3), R(4), C(4)); 
   Sumador5: FA port map (A(5), B(5), C(4), R(5), C(5)); 
   Sumador6: FA port map (A(6), B(6), C(5), R(6), C(6)); 
   Sumador7: FA port map (A(7), B(7), C(6), R(7), cout => w); 
   cout <= w;
   v <= w xor C(6);
 end archSumador;

Proyecto/Unidad_Aritmetica/Sumador8Bits_tb.vhd
library IEEE;
use IEEE.std_logic_1164.all;

entity Sumador8Bits_tb is
end entity Sumador8Bits_tb;

architecture arch of Sumador8Bits_tb is
    component Sumador8Bits
        port (
            A, B: in std_logic_vector (7 downto 0);
            cin: in std_logic;
            R: out std_logic_vector (7 downto 0); 
            cout: out std_logic;
            v: out std_logic
        );
    end component;

    signal A_tb: std_logic_vector(7 downto 0);
    signal B_tb: std_logic_vector(7 downto 0);
    signal cin_tb: std_logic;
    signal R_tb: std_logic_vector(7 downto 0);
    signal cout_tb: std_logic;
    signal v_tb: std_logic;

begin
    test: Sumador8Bits port map (A => A_tb, B => B_tb, cin => cin_tb, R => R_tb, cout => cout_tb, v => v_tb);
  
    -- Proceso de estímulo
    process
    begin
        -- Valores de entrada de prueba
        A_tb <= "00000000";
        B_tb <= "10010011";
        cin_tb <= '0';
        wait for 10 ns;

        -- Valores de entrada de prueba
        A_tb <= "11111111";
        B_tb <= "00001111";
        cin_tb <= '1';
        wait for 10 ns;

        -- Valores de entrada de prueba
        A_tb <= "01010101";
        B_tb <= "10101010";
        cin_tb <= '0';
        wait for 10 ns;

        -- Valores de entrada de prueba
        A_tb <= "00110011";
        B_tb <= "11001100";
        cin_tb <= '1';
        wait for 10 ns;

        -- Valores de entrada de prueba
        A_tb <= "10010011";
        B_tb <= "01001110";
        cin_tb <= '0';
        wait for 10 ns;

        -- Valores de entrada de prueba
        A_tb <= "01001110";
        B_tb <= "10010011";
        cin_tb <= '1';
        wait for 10 ns;

        -- Valores de entrada de prueba
        A_tb <= "10101010";
        B_tb <= "10101010";
        cin_tb <= '0';
        wait for 10 ns;

        -- Valores de entrada de prueba
        A_tb <= "11110000";
        B_tb <= "00001111";
        cin_tb <= '1';
        wait for 10 ns;

        wait;
    end process;
end architecture arch;

Proyecto/Unidad_Aritmetica/Sumador8Bits.vcd
$date
  Sun Jun 18 14:24:27 2023
$end
$version
  GHDL v0
$end
$timescale
  1 fs
$end
$scope module standard $end
$upscope $end
$scope module std_logic_1164 $end
$upscope $end
$scope module sumador8bits_tb $end
$var reg 8 ! a_tb[7:0] $end
$var reg 8 " b_tb[7:0] $end
$var reg 1 # cin_tb $end
$var reg 8 $ r_tb[7:0] $end
$var reg 1 % cout_tb $end
$var reg 1 & v_tb $end
$scope module test $end
$var reg 8 ' a[7:0] $end
$var reg 8 ( b[7:0] $end
$var reg 1 ) cin $end
$var reg 8 * r[7:0] $end
$var reg 1 + cout $end
$var reg 1 , v $end
$var reg 7 - c[6:0] $end
$var reg 1 . w $end
$scope module sumador0 $end
$var reg 1 / a $end
$var reg 1 0 b $end
$var reg 1 1 cin $end
$var reg 1 2 r $end
$var reg 1 3 cout $end
$upscope $end
$scope module sumador1 $end
$var reg 1 4 a $end
$var reg 1 5 b $end
$var reg 1 6 cin $end
$var reg 1 7 r $end
$var reg 1 8 cout $end
$upscope $end
$scope module sumador2 $end
$var reg 1 9 a $end
$var reg 1 : b $end
$var reg 1 ; cin $end
$var reg 1 < r $end
$var reg 1 = cout $end
$upscope $end
$scope module sumador3 $end
$var reg 1 > a $end
$var reg 1 ? b $end
$var reg 1 @ cin $end
$var reg 1 A r $end
$var reg 1 B cout $end
$upscope $end
$scope module sumador4 $end
$var reg 1 C a $end
$var reg 1 D b $end
$var reg 1 E cin $end
$var reg 1 F r $end
$var reg 1 G cout $end
$upscope $end
$scope module sumador5 $end
$var reg 1 H a $end
$var reg 1 I b $end
$var reg 1 J cin $end
$var reg 1 K r $end
$var reg 1 L cout $end
$upscope $end
$scope module sumador6 $end
$var reg 1 M a $end
$var reg 1 N b $end
$var reg 1 O cin $end
$var reg 1 P r $end
$var reg 1 Q cout $end
$upscope $end
$scope module sumador7 $end
$var reg 1 R a $end
$var reg 1 S b $end
$var reg 1 T cin $end
$var reg 1 U r $end
$var reg 1 V cout $end
$upscope $end
$upscope $end
$upscope $end
$enddefinitions $end
#0
b00000000 !
b10010011 "
0#
b10010011 $
0%
0&
b00000000 '
b10010011 (
0)
b10010011 *
0+
0,
b0000000 -
0.
0/
10
01
12
03
04
15
06
17
08
09
0:
0;
0<
0=
0>
0?
0@
0A
0B
0C
1D
0E
1F
0G
0H
0I
0J
0K
0L
0M
0N
0O
0P
0Q
0R
1S
0T
1U
0V
#10000000
b11111111 !
b00001111 "
1#
b00001111 $
1%
0&
b11111111 '
b00001111 (
1)
b00001111 *
1+
0,
b1111111 -
1.
1/
11
13
14
16
17
18
19
1:
1;
1<
1=
1>
1?
1@
1A
1B
1C
0D
1E
0F
1G
1H
1J
0K
1L
1M
1O
0P
1Q
1R
0S
1T
0U
1V
#20000000
b01010101 !
b10101010 "
0#
b11111111 $
0%
0&
b01010101 '
b10101010 (
0)
b11111111 *
0+
0,
b0000000 -
0.
00
01
03
04
06
17
08
0:
0;
1<
0=
0>
0@
1A
0B
0E
1F
0G
0H
1I
0J
1K
0L
0O
1P
0Q
0R
1S
0T
1U
0V
#30000000
b00110011 !
b11001100 "
1#
b00000000 $
1%
0&
b00110011 '
b11001100 (
1)
b00000000 *
1+
0,
b1111111 -
1.
11
02
13
14
05
16
07
18
09
1:
1;
0<
1=
1@
0A
1B
1E
0F
1G
1H
0I
1J
0K
1L
0M
1N
1O
0P
1Q
1T
0U
1V
#40000000
b10010011 !
b01001110 "
0#
b11100001 $
0%
0&
b10010011 '
b01001110 (
0)
b11100001 *
0+
0,
b0011110 -
0.
01
12
03
15
06
07
0H
1K
0L
0O
1P
0Q
1R
0S
0T
1U
0V
#50000000
b01001110 !
b10010011 "
1#
b11100010 $
b01001110 '
b10010011 (
1)
b11100010 *
b0011111 -
0/
10
11
02
13
16
17
19
0:
1>
0?
0C
1D
1M
0N
0R
1S
#60000000
b10101010 !
b10101010 "
0#
b01010100 $
1%
1&
b10101010 '
b10101010 (
0)
b01010100 *
1+
1,
b0101010 -
1.
00
01
03
06
07
09
1<
0=
1?
0@
0A
0D
1F
0G
1H
1I
0J
0K
1L
0M
1O
1P
1R
0U
1V
#70000000
b11110000 !
b00001111 "
1#
b00000000 $
1%
0&
b11110000 '
b00001111 (
1)
b00000000 *
1+
0,
b1111111 -
1.
10
11
13
04
16
07
18
1:
1;
0<
1=
0>
1@
0A
1B
1C
1E
0F
1G
0I
1J
0K
1L
1M
1O
0P
1Q
0S
1T
0U
1V
