Proyecto/Mux2a1_8bits/Mux2a1.vhd
--Multiplexor 2 a 1
library IEEE;
use IEEE.std_logic_1164.all;

entity Mux2a1 is
--a se selecciona con s = 1, y b con s = 0.
  port 
  (
    A, B: in std_logic_vector (7 downto 0);
    set: in std_logic;
    r: out std_logic_vector (7 downto 0)
  );
  end Mux2a1;

architecture Ar_Mux2a1 of Mux2a1 is
  begin
    with set select
      r <= A when '1',
           B when others;

end architecture Ar_Mux2a1;

Proyecto/UnidadFuncional/Mux8a1A.vhd
library ieee;
use ieee.std_logic_1164.all;

entity Mux8a1A is
    port(
        a1,a2,a3,a4,a5,a6,a7,a8: in std_logic;
        s: in std_logic_vector(2 downto 0);
        R: out std_logic
    );
end entity Mux8a1A;

architecture Ar_Mux8a1 of Mux8a1A is
    begin
        with s select 
            R <= a1 when "000",
                 a2 when "001",
                 a3 when "010",
                 a4 when "011",
                 a5 when "100",
                 a6 when "101",
                 a7 when "110",
                 a8 when others;
    end Ar_Mux8a1;

-- https://scuolaelettrica.it/escuelaelectrica/elettronica/lezione2.php

Proyecto/UL/UnidadLogica.vhd
library ieee;
use ieee.std_logic_1164.all;

entity UnidadLogica is
    port (
            A, B: in std_logic_vector (7 downto 0);
            s: in std_logic_vector (2 downto 0);
            Result: out std_logic_vector(7 downto 0)
        );
end entity UnidadLogica;

architecture Ar_UnidadLogica of UnidadLogica is
    component Mux8a1A
        port (
            a1,a2,a3,a4,a5,a6,a7,a8: in std_logic;
            S : in std_logic_vector(2 downto 0);
            R : out std_logic
        );
    end component;

    signal andM: std_logic_vector (7 downto 0);
    signal orM: std_logic_vector (7 downto 0);
    signal notA: std_logic_vector (7 downto 0);
    signal notB: std_logic_vector (7 downto 0);  
    signal xorM: std_logic_vector (7 downto 0);  
    signal norM: std_logic_vector (7 downto 0);
    signal nandM: std_logic_vector (7 downto 0);
    signal R: std_logic_vector(7 downto 0);

    begin 
   
    andM <= A and B;
    orM <= A or B;
    notA <= not(A);
    notB <= not(B);
    xorM <= A xor B;
    xnorM <= A xnor B;
    norM <= A nor B;
    nandM <= A nand B;

        mux1: Mux8a1A port map(andM(0),orM(0),notA(0),notB(0),xorM(0),norM(0),nandM(0),xnorM(0),s,Result(0));
        mux2: Mux8a1A port map(andM(1),orM(1),notA(1),notB(1),xorM(1),norM(1),nandM(1),xnorM(1),s,Result(1));
        mux3: Mux8a1A port map(andM(2),orM(2),notA(2),notB(2),xorM(2),norM(2),nandM(2),xnorM(2),s,Result(2));
        mux4: Mux8a1A port map(andM(3),orM(3),notA(3),notB(3),xorM(3),norM(3),nandM(3),xnorM(3),s,Result(3));
        mux5: Mux8a1A port map(andM(4),orM(4),notA(4),notB(4),xorM(4),norM(4),nandM(4),xnorM(4),s,Result(4));
        mux6: Mux8a1A port map(andM(5),orM(5),notA(5),notB(5),xorM(5),norM(5),nandM(5),xnorM(5),s,Result(5));
        mux7: Mux8a1A port map(andM(6),orM(6),notA(6),notB(6),xorM(6),norM(6),nandM(6),xnorM(6),s,Result(6));
        mux8: Mux8a1A port map(andM(7),orM(7),notA(7),notB(7),xorM(7),norM(7),nandM(7),xnorM(7),s,Result(7));
       
end architecture Ar_UnidadLogica;
        
--AND, OR, NOT, XOR, NAND, NOR

Proyecto/UnidadFuncional/FA.vhd
library IEEE;
use IEEE.std_logic_1164.all;

 entity FA is
 
   port (a, b, cin: in std_logic;
         r, cout: out std_logic);
 end FA;
 
 architecture archFA of FA is
 begin
   cout <= (a and cin) or (a and b) or (b and cin);
   r <= (a xor (b xor cin));
 end archFA;

Proyecto/ALU2.0/Sumador8Bits.vhd

library IEEE;
use IEEE.std_logic_1164.all;


 entity Sumador8Bits is
   port (A, B: in std_logic_vector (7 downto 0);
         cin: in std_logic;
         R: out std_logic_vector (7 downto 0); 
         cout: out std_logic;
         v: out std_logic);
 end Sumador8Bits;
 
 architecture archSumador of Sumador8Bits is
   component FA
     port (a, b, cin: in std_logic;
           r, cout: out std_logic);
   end component;

 signal C : std_logic_vector (6 downto 0);
 signal w : std_logic;

 begin
   Sumador0: FA port map (A(0), B(0), cin, R(0), C(0)); 
   Sumador1: FA port map (A(1), B(1), C(0), R(1), C(1)); 
   Sumador2: FA port map (A(2), B(2), C(1), R(2), C(2)); 
   Sumador3: FA port map (A(3), B(3), C(2), R(3), C(3)); 
   Sumador4: FA port map (A(4), B(4), C(3), R(4), C(4)); 
   Sumador5: FA port map (A(5), B(5), C(4), R(5), C(5)); 
   Sumador6: FA port map (A(6), B(6), C(5), R(6), C(6)); 
   Sumador7: FA port map (A(7), B(7), C(6), R(7), cout => w); 
   cout <= w;
   v <= w xor C(6);
 end archSumador;

Proyecto/Unidad_Aritmetica/Unidad_Aritmetica.vhd
library IEEE;
use IEEE.std_logic_1164.all;

entity Unidad_Aritmetica is
	port (
		A, B: in std_logic_vector(7 downto 0);
		S : in std_logic_vector(2 downto 0);
		R: out std_logic_vector(7 downto 0);
		cout: out std_logic;
		v: out std_logic
	);
end Unidad_Aritmetica;

architecture arch of Unidad_Aritmetica is
	component Sumador8Bits is
		port (
			A, B: in std_logic_vector (7 downto 0);
			cin: in std_logic;
			R: out std_logic_vector (7 downto 0);
			cout: out std_logic;
			v: out std_logic
		);
	end component Sumador8Bits;

	signal Ap, Bp: std_logic_vector(7 downto 0);
	signal cin: std_logic;

	begin

	-- Ap = AS2’S1’ + AS0’ + S2S1’S0
	Ap(0) <= (A(0) and not(S(2)) and not(S(1))) or (A(0) and not(S(0))) or (S(2) and not(S(1)) and S(0));
    Ap(1) <= (A(1) and not(S(2)) and not(S(1))) or (A(1) and not(S(0))) or (S(2) and not(S(1)) and S(0));
    Ap(2) <= (A(2) and not(S(2)) and not(S(1))) or (A(2) and not(S(0))) or (S(2) and not(S(1)) and S(0));
    Ap(3) <= (A(3) and not(S(2)) and not(S(1))) or (A(3) and not(S(0))) or (S(2) and not(S(1)) and S(0));
    Ap(4) <= (A(4) and not(S(2)) and not(S(1))) or (A(4) and not(S(0))) or (S(2) and not(S(1)) and S(0));
    Ap(5) <= (A(5) and not(S(2)) and not(S(1))) or (A(5) and not(S(0))) or (S(2) and not(S(1)) and S(0));
    Ap(6) <= (A(6) and not(S(2)) and not(S(1))) or (A(6) and not(S(0))) or (S(2) and not(S(1)) and S(0));
    Ap(7) <= (A(7) and not(S(2)) and not(S(1))) or (A(7) and not(S(0))) or (S(2) and not(S(1)) and S(0));

	-- Bp = BS2’S1’S0’ + B’S2’S1’S0 + BS1S0 + S2S1’S0’ + BS2S0
	Bp(0) <= ((B(0) and not(S(2)) and not(S(1)) and not(S(0))) or (not(B(0)) and not(S(2)) and not(S(1)) and S(0)) or (B(0) and S(1) and S(0)) or (S(2) and not(S(1)) and not(S(0))) or (B(0) and S(2) and S(0)));
	Bp(1) <= ((B(1) and not(S(2)) and not(S(1)) and not(S(0))) or (not(B(1)) and not(S(2)) and not(S(1)) and S(0)) or (B(1) and S(1) and S(0)) or (S(2) and not(S(1)) and not(S(0))) or (B(1) and S(2) and S(0)));
	Bp(2) <= ((B(2) and not(S(2)) and not(S(1)) and not(S(0))) or (not(B(2)) and not(S(2)) and not(S(1)) and S(0)) or (B(2) and S(1) and S(0)) or (S(2) and not(S(1)) and not(S(0))) or (B(2) and S(2) and S(0)));
	Bp(3) <= ((B(3) and not(S(2)) and not(S(1)) and not(S(0))) or (not(B(3)) and not(S(2)) and not(S(1)) and S(0)) or (B(3) and S(1) and S(0)) or (S(2) and not(S(1)) and not(S(0))) or (B(3) and S(2) and S(0)));
	Bp(4) <= ((B(4) and not(S(2)) and not(S(1)) and not(S(0))) or (not(B(4)) and not(S(2)) and not(S(1)) and S(0)) or (B(4) and S(1) and S(0)) or (S(2) and not(S(1)) and not(S(0))) or (B(4) and S(2) and S(0)));
	Bp(5) <= ((B(5) and not(S(2)) and not(S(1)) and not(S(0))) or (not(B(5)) and not(S(2)) and not(S(1)) and S(0)) or (B(5) and S(1) and S(0)) or (S(2) and not(S(1)) and not(S(0))) or (B(5) and S(2) and S(0)));
	Bp(6) <= ((B(6) and not(S(2)) and not(S(1)) and not(S(0))) or (not(B(6)) and not(S(2)) and not(S(1)) and S(0)) or (B(6) and S(1) and S(0)) or (S(2) and not(S(1)) and not(S(0))) or (B(6) and S(2) and S(0)));
	Bp(7) <= ((B(7) and not(S(2)) and not(S(1)) and not(S(0))) or (not(B(7)) and not(S(2)) and not(S(1)) and S(0)) or (B(7) and S(1) and S(0)) or (S(2) and not(S(1)) and not(S(0))) or (B(7) and S(2) and S(0)));

	--S2’S0 + S2’S1
	cin <= (not(S(2)) and S(0)) or (not(S(2)) and S(1));

	Sum1: Sumador8Bits port map (Ap, Bp, cin, R, cout, v);

end arch;

Proyecto/ALU2.0/ALU.vhd
library IEEE;
use IEEE.std_logic_1164.all;

entity ALU is
    port(
        A: in std_logic_vector(7 downto 0);
        B: in std_logic_vector(7 downto 0);
        S: in std_logic_vector(3 downto 0);
        R: out std_logic_vector(7 downto 0);
        cout: out std_logic;
        v: out std_logic
    );
end ALU;
--S(3,2,1,0);
architecture arch of ALU is

    component Unidad_Aritmetica is
        port (
            A, B: in std_logic_vector(7 downto 0);
            S: in std_logic_vector(2 downto 0);
            R: out std_logic_vector(7 downto 0);
            cout: out std_logic;
            v: out std_logic
	    );
    end component;

    component UnidadLogica is 
        port (
            A, B: in std_logic_vector (7 downto 0);
            s: in std_logic_vector (2 downto 0);
            Result: out std_logic_vector(7 downto 0)
        );
    end component;

    component Mux2a1 is
        port(
            A, B: in std_logic_vector (7 downto 0);
            set: in std_logic;
            r: out std_logic_vector (7 downto 0)
        );  
    end component; 

    signal auxUS: std_logic_vector(2 downto 0);
    signal UA_1: std_logic_vector(7 downto 0);
    signal UL_1: std_logic_vector(7 downto 0);


    begin
        auxUS(0) <= S(0);
        auxUS(1) <= S(1);
        auxUS(2) <= S(2);

        UA2: Unidad_Aritmetica port map(A, B, auxUS, UA_1, cout, v);
        UL2: UnidadLogica port map(A, B, auxUS, UL_1);
        MUX2: Mux2a1 port map(UA_1, UL_1, S(3), R);
end arch;

Proyecto/ALU2.0/ALU_tb.vhd
library IEEE;
use IEEE.std_logic_1164.all;

entity ALU_tb is 
end ALU_tb;

architecture arch of ALU_tb is

    component ALU is
        port(
            A: in std_logic_vector(7 downto 0);
            B: in std_logic_vector(7 downto 0);
            S: in std_logic_vector(3 downto 0);
            R: out std_logic_vector(7 downto 0);
            cout: out std_logic;
            v: out std_logic
        );
    end component;

    signal x: std_logic_vector(7 downto 0);
    signal y: std_logic_vector(7 downto 0);
    signal senal: std_logic_vector(3 downto 0);
    signal resulto: std_logic_vector(7 downto 0);
    signal R: std_logic_vector(7 downto 0);
    signal cou: std_logic;
    signal v: std_logic;

    begin   
        x <= "00001111";
        y <= "00000011";

        Alupas: ALU port map(x,y,senal,R,cou,v);
        senal <= "1000" after 0 ns, "1001" after 5 ns, "1010" after 10 ns, "1011" after 15 ns, "1100" after 20 ns, "1101" after 25 ns, "1110" after 30 ns, "1111" after 35 ns, "1000" after 40 ns;


end arch;

Proyecto/ALU2.0/ALU.vcd
$date
  Tue Jun 20 13:38:39 2023
$end
$version
  GHDL v0
$end
$timescale
  1 fs
$end
$scope module standard $end
$upscope $end
$scope module std_logic_1164 $end
$upscope $end
$scope module alu_tb $end
$var reg 8 ! x[7:0] $end
$var reg 8 " y[7:0] $end
$var reg 4 # senal[3:0] $end
$var reg 8 $ resulto[7:0] $end
$var reg 8 % r[7:0] $end
$var reg 1 & cou $end
$var reg 1 ' v $end
$scope module alupas $end
$var reg 8 ( a[7:0] $end
$var reg 8 ) b[7:0] $end
$var reg 4 * s[3:0] $end
$var reg 8 + r[7:0] $end
$var reg 1 , cout $end
$var reg 1 - v $end
$var reg 3 . auxus[2:0] $end
$var reg 8 / ua_1[7:0] $end
$var reg 8 0 ul_1[7:0] $end
$scope module ua2 $end
$var reg 8 1 a[7:0] $end
$var reg 8 2 b[7:0] $end
$var reg 3 3 s[2:0] $end
$var reg 8 4 r[7:0] $end
$var reg 1 5 cout $end
$var reg 1 6 v $end
$var reg 8 7 ap[7:0] $end
$var reg 8 8 bp[7:0] $end
$var reg 1 9 cin $end
$scope module sum1 $end
$var reg 8 : a[7:0] $end
$var reg 8 ; b[7:0] $end
$var reg 1 < cin $end
$var reg 8 = r[7:0] $end
$var reg 1 > cout $end
$var reg 1 ? v $end
$var reg 7 @ c[6:0] $end
$var reg 1 A w $end
$scope module sumador0 $end
$var reg 1 B a $end
$var reg 1 C b $end
$var reg 1 D cin $end
$var reg 1 E r $end
$var reg 1 F cout $end
$upscope $end
$scope module sumador1 $end
$var reg 1 G a $end
$var reg 1 H b $end
$var reg 1 I cin $end
$var reg 1 J r $end
$var reg 1 K cout $end
$upscope $end
$scope module sumador2 $end
$var reg 1 L a $end
$var reg 1 M b $end
$var reg 1 N cin $end
$var reg 1 O r $end
$var reg 1 P cout $end
$upscope $end
$scope module sumador3 $end
$var reg 1 Q a $end
$var reg 1 R b $end
$var reg 1 S cin $end
$var reg 1 T r $end
$var reg 1 U cout $end
$upscope $end
$scope module sumador4 $end
$var reg 1 V a $end
$var reg 1 W b $end
$var reg 1 X cin $end
$var reg 1 Y r $end
$var reg 1 Z cout $end
$upscope $end
$scope module sumador5 $end
$var reg 1 [ a $end
$var reg 1 \ b $end
$var reg 1 ] cin $end
$var reg 1 ^ r $end
$var reg 1 _ cout $end
$upscope $end
$scope module sumador6 $end
$var reg 1 ` a $end
$var reg 1 a b $end
$var reg 1 b cin $end
$var reg 1 c r $end
$var reg 1 d cout $end
$upscope $end
$scope module sumador7 $end
$var reg 1 e a $end
$var reg 1 f b $end
$var reg 1 g cin $end
$var reg 1 h r $end
$var reg 1 i cout $end
$upscope $end
$upscope $end
$upscope $end
$scope module ul2 $end
$var reg 8 j a[7:0] $end
$var reg 8 k b[7:0] $end
$var reg 3 l s[2:0] $end
$var reg 8 m result[7:0] $end
$var reg 8 n andm[7:0] $end
$var reg 8 o orm[7:0] $end
$var reg 8 p nota[7:0] $end
$var reg 8 q notb[7:0] $end
$var reg 8 r xnorm[7:0] $end
$var reg 8 s norm[7:0] $end
$var reg 8 t nandm[7:0] $end
$var reg 8 u xorm[7:0] $end
$var reg 8 v r[7:0] $end
$scope module mux1 $end
$var reg 1 w a1 $end
$var reg 1 x a2 $end
$var reg 1 y a3 $end
$var reg 1 z a4 $end
$var reg 1 { a5 $end
$var reg 1 | a6 $end
$var reg 1 } a7 $end
$var reg 1 !" a8 $end
$var reg 3 "" s[2:0] $end
$var reg 1 #" r $end
$upscope $end
$scope module mux2 $end
$var reg 1 $" a1 $end
$var reg 1 %" a2 $end
$var reg 1 &" a3 $end
$var reg 1 '" a4 $end
$var reg 1 (" a5 $end
$var reg 1 )" a6 $end
$var reg 1 *" a7 $end
$var reg 1 +" a8 $end
$var reg 3 ," s[2:0] $end
$var reg 1 -" r $end
$upscope $end
$scope module mux3 $end
$var reg 1 ." a1 $end
$var reg 1 /" a2 $end
$var reg 1 0" a3 $end
$var reg 1 1" a4 $end
$var reg 1 2" a5 $end
$var reg 1 3" a6 $end
$var reg 1 4" a7 $end
$var reg 1 5" a8 $end
$var reg 3 6" s[2:0] $end
$var reg 1 7" r $end
$upscope $end
$scope module mux4 $end
$var reg 1 8" a1 $end
$var reg 1 9" a2 $end
$var reg 1 :" a3 $end
$var reg 1 ;" a4 $end
$var reg 1 <" a5 $end
$var reg 1 =" a6 $end
$var reg 1 >" a7 $end
$var reg 1 ?" a8 $end
$var reg 3 @" s[2:0] $end
$var reg 1 A" r $end
$upscope $end
$scope module mux5 $end
$var reg 1 B" a1 $end
$var reg 1 C" a2 $end
$var reg 1 D" a3 $end
$var reg 1 E" a4 $end
$var reg 1 F" a5 $end
$var reg 1 G" a6 $end
$var reg 1 H" a7 $end
$var reg 1 I" a8 $end
$var reg 3 J" s[2:0] $end
$var reg 1 K" r $end
$upscope $end
$scope module mux6 $end
$var reg 1 L" a1 $end
$var reg 1 M" a2 $end
$var reg 1 N" a3 $end
$var reg 1 O" a4 $end
$var reg 1 P" a5 $end
$var reg 1 Q" a6 $end
$var reg 1 R" a7 $end
$var reg 1 S" a8 $end
$var reg 3 T" s[2:0] $end
$var reg 1 U" r $end
$upscope $end
$scope module mux7 $end
$var reg 1 V" a1 $end
$var reg 1 W" a2 $end
$var reg 1 X" a3 $end
$var reg 1 Y" a4 $end
$var reg 1 Z" a5 $end
$var reg 1 [" a6 $end
$var reg 1 \" a7 $end
$var reg 1 ]" a8 $end
$var reg 3 ^" s[2:0] $end
$var reg 1 _" r $end
$upscope $end
$scope module mux8 $end
$var reg 1 `" a1 $end
$var reg 1 a" a2 $end
$var reg 1 b" a3 $end
$var reg 1 c" a4 $end
$var reg 1 d" a5 $end
$var reg 1 e" a6 $end
$var reg 1 f" a7 $end
$var reg 1 g" a8 $end
$var reg 3 h" s[2:0] $end
$var reg 1 i" r $end
$upscope $end
$upscope $end
$scope module mux2 $end
$var reg 8 j" a[7:0] $end
$var reg 8 k" b[7:0] $end
$var reg 1 l" set $end
$var reg 8 m" r[7:0] $end
$upscope $end
$upscope $end
$upscope $end
$enddefinitions $end
#0
b00001111 !
b00000011 "
b1000 #
bUUUUUUUU $
b00010010 %
0&
0'
b00001111 (
b00000011 )
b1000 *
b00010010 +
0,
0-
b000 .
b00010010 /
b00000011 0
b00001111 1
b00000011 2
b000 3
b00010010 4
05
06
b00001111 7
b00000011 8
09
b00001111 :
b00000011 ;
0<
b00010010 =
0>
0?
b0001111 @
0A
1B
1C
0D
0E
1F
1G
1H
1I
1J
1K
1L
0M
1N
0O
1P
1Q
0R
1S
0T
1U
0V
0W
1X
1Y
0Z
0[
0\
0]
0^
0_
0`
0a
0b
0c
0d
0e
0f
0g
0h
0i
b00001111 j
b00000011 k
b000 l
b00000011 m
b00000011 n
b00001111 o
b11110000 p
b11111100 q
b11110011 r
b11110000 s
b11111100 t
b00001100 u
bUUUUUUUU v
1w
1x
0y
0z
0{
0|
0}
1!"
b000 ""
1#"
1$"
1%"
0&"
0'"
0("
0)"
0*"
1+"
b000 ,"
1-"
0."
1/"
00"
11"
12"
03"
14"
05"
b000 6"
07"
08"
19"
0:"
1;"
1<"
0="
1>"
0?"
b000 @"
0A"
0B"
0C"
1D"
1E"
0F"
1G"
1H"
1I"
b000 J"
0K"
0L"
0M"
1N"
1O"
0P"
1Q"
1R"
1S"
b000 T"
0U"
0V"
0W"
1X"
1Y"
0Z"
1["
1\"
1]"
b000 ^"
0_"
0`"
0a"
1b"
1c"
0d"
1e"
1f"
1g"
b000 h"
0i"
b00010010 j"
b00000011 k"
1l"
b00010010 m"
#5000000
b1001 #
b00001100 %
1&
0'
b1001 *
b00001100 +
1,
0-
b001 .
b00001100 /
b00001111 0
b001 3
b00001100 4
15
06
b11111100 8
19
b11111100 ;
1<
b00001100 =
1>
0?
b1111111 @
1A
0C
1D
0H
0J
1M
1O
1R
1T
1W
0Y
1Z
1\
1]
0^
1_
1a
1b
0c
1d
1f
1g
0h
1i
b001 l
b00001111 m
b001 ""
b001 ,"
b001 6"
17"
b001 @"
1A"
b001 J"
b001 T"
b001 ^"
b001 h"
b00001100 j"
b00001111 k"
b00001100 m"
#10000000
b1010 #
b00010000 %
0&
b1010 *
b00010000 +
0,
b010 .
b00010000 /
b11110000 0
b010 3
b00010000 4
05
b00000000 8
b00000000 ;
b00010000 =
0>
b0001111 @
0A
0M
0O
0R
0T
0W
1Y
0Z
0\
0]
0^
0_
0a
0b
0c
0d
0f
0g
0h
0i
b010 l
b11110000 m
b010 ""
0#"
b010 ,"
0-"
b010 6"
07"
b010 @"
0A"
b010 J"
1K"
b010 T"
1U"
b010 ^"
1_"
b010 h"
1i"
b00010000 j"
b11110000 k"
b00010000 m"
#15000000
b1011 #
b00000100 %
b1011 *
b00000100 +
b011 .
b00000100 /
b11111100 0
b011 3
b00000100 4
b00000000 7
b00000011 8
b00000000 :
b00000011 ;
b00000100 =
b0000011 @
0B
1C
0G
1H
0L
1O
0P
0Q
0S
0T
0U
0X
0Y
b011 l
b11111100 m
b011 ""
b011 ,"
b011 6"
17"
b011 @"
1A"
b011 J"
b011 T"
b011 ^"
b011 h"
b00000100 j"
b11111100 k"
b00000100 m"
#20000000
b1100 #
b00001110 %
1&
0'
b1100 *
b00001110 +
1,
0-
b100 .
b00001110 /
b00001100 0
b100 3
b00001110 4
15
06
b00001111 7
b11111111 8
09
b00001111 :
b11111111 ;
0<
b00001110 =
1>
0?
b1111111 @
1A
1B
0D
1G
1J
1L
1M
1P
1Q
1R
1S
1T
1U
1W
1X
0Y
1Z
1\
1]
0^
1_
1a
1b
0c
1d
1f
1g
0h
1i
b100 l
b00001100 m
b100 ""
b100 ,"
b100 6"
b100 @"
b100 J"
0K"
b100 T"
0U"
b100 ^"
0_"
b100 h"
0i"
b00001110 j"
b00001100 k"
b00001110 m"
#25000000
b1101 #
b00000010 %
b1101 *
b00000010 +
b101 .
b00000010 /
b11110000 0
b101 3
b00000010 4
b11111111 7
b00000011 8
b11111111 :
b00000011 ;
b00000010 =
0M
0O
0R
0T
1V
0W
1[
0\
1`
0a
1e
0f
b101 l
b11110000 m
b101 ""
b101 ,"
b101 6"
07"
b101 @"
0A"
b101 J"
1K"
b101 T"
1U"
b101 ^"
1_"
b101 h"
1i"
b00000010 j"
b11110000 k"
b00000010 m"
#30000000
b1110 #
b00001111 %
0&
b1110 *
b00001111 +
0,
b110 .
b00001111 /
b11111100 0
b110 3
b00001111 4
05
b00001111 7
b00000000 8
b00001111 :
b00000000 ;
b00001111 =
0>
b0000000 @
0A
0C
1E
0F
0H
0I
1J
0K
0N
1O
0P
0S
1T
0U
0V
0X
0Y
0Z
0[
0]
0^
0_
0`
0b
0c
0d
0e
0g
0h
0i
b110 l
b11111100 m
b110 ""
b110 ,"
b110 6"
17"
b110 @"
1A"
b110 J"
b110 T"
b110 ^"
b110 h"
b00001111 j"
b11111100 k"
b00001111 m"
#35000000
b1111 #
b00000011 %
b1111 *
b00000011 +
b111 .
b00000011 /
b11110011 0
b111 3
b00000011 4
b00000000 7
b00000011 8
b00000000 :
b00000011 ;
b00000011 =
0B
1C
0G
1H
0L
0O
0Q
0T
b111 l
b11110011 m
b111 ""
1#"
b111 ,"
1-"
b111 6"
07"
b111 @"
0A"
b111 J"
b111 T"
b111 ^"
b111 h"
b00000011 j"
b11110011 k"
b00000011 m"
#40000000
b1000 #
b00010010 %
b1000 *
b00010010 +
b000 .
b00010010 /
b00000011 0
b000 3
b00010010 4
b00001111 7
b00001111 :
b00010010 =
b0001111 @
1B
0E
1F
1G
1I
1J
1K
1L
1N
0O
1P
1Q
1S
0T
1U
1X
1Y
b000 l
b00000011 m
b000 ""
b000 ,"
b000 6"
b000 @"
b000 J"
0K"
b000 T"
0U"
b000 ^"
0_"
b000 h"
0i"
b00010010 j"
b00000011 k"
b00010010 m"
