Proyecto/UnidadFuncional/FA.vhd
library IEEE;
use IEEE.std_logic_1164.all;

 entity FA is
 
   port (a, b, cin: in std_logic;
         r, cout: out std_logic);
 end FA;
 
 architecture archFA of FA is
 begin
   cout <= (a and cin) or (a and b) or (b and cin);
   r <= (a xor (b xor cin));
 end archFA;

Proyecto/ALU2.0/Sumador8Bits.vhd

library IEEE;
use IEEE.std_logic_1164.all;


 entity Sumador8Bits is
   port (A, B: in std_logic_vector (7 downto 0);
         cin: in std_logic;
         R: out std_logic_vector (7 downto 0); 
         cout: out std_logic;
         v: out std_logic);
 end Sumador8Bits;
 
 architecture archSumador of Sumador8Bits is
   component FA
     port (a, b, cin: in std_logic;
           r, cout: out std_logic);
   end component;

 signal C : std_logic_vector (6 downto 0);
 signal w : std_logic;

 begin
   Sumador0: FA port map (A(0), B(0), cin, R(0), C(0)); 
   Sumador1: FA port map (A(1), B(1), C(0), R(1), C(1)); 
   Sumador2: FA port map (A(2), B(2), C(1), R(2), C(2)); 
   Sumador3: FA port map (A(3), B(3), C(2), R(3), C(3)); 
   Sumador4: FA port map (A(4), B(4), C(3), R(4), C(4)); 
   Sumador5: FA port map (A(5), B(5), C(4), R(5), C(5)); 
   Sumador6: FA port map (A(6), B(6), C(5), R(6), C(6)); 
   Sumador7: FA port map (A(7), B(7), C(6), R(7), cout => w); 
   cout <= w;
   v <= w xor C(6);
 end archSumador;

Proyecto/Unidad_Aritmetica/Unidad_Aritmetica.vhd
library IEEE;
use IEEE.std_logic_1164.all;

entity Unidad_Aritmetica is
	port (
		A, B: in std_logic_vector(7 downto 0);
		S : in std_logic_vector(2 downto 0);
		R: out std_logic_vector(7 downto 0);
		cout: out std_logic;
		v: out std_logic
	);
end Unidad_Aritmetica;

architecture arch of Unidad_Aritmetica is
	component Sumador8Bits is
		port (
			A, B: in std_logic_vector (7 downto 0);
			cin: in std_logic;
			R: out std_logic_vector (7 downto 0);
			cout: out std_logic;
			v: out std_logic
		);
	end component Sumador8Bits;

	signal Ap, Bp: std_logic_vector(7 downto 0);
	signal cin: std_logic;

	begin

	-- Ap = AS2’S1’ + AS0’ + S2S1’S0
	Ap(0) <= (A(0) and not(S(2)) and not(S(1))) or (A(0) and not(S(0))) or (S(2) and not(S(1)) and S(0));
    Ap(1) <= (A(1) and not(S(2)) and not(S(1))) or (A(1) and not(S(0))) or (S(2) and not(S(1)) and S(0));
    Ap(2) <= (A(2) and not(S(2)) and not(S(1))) or (A(2) and not(S(0))) or (S(2) and not(S(1)) and S(0));
    Ap(3) <= (A(3) and not(S(2)) and not(S(1))) or (A(3) and not(S(0))) or (S(2) and not(S(1)) and S(0));
    Ap(4) <= (A(4) and not(S(2)) and not(S(1))) or (A(4) and not(S(0))) or (S(2) and not(S(1)) and S(0));
    Ap(5) <= (A(5) and not(S(2)) and not(S(1))) or (A(5) and not(S(0))) or (S(2) and not(S(1)) and S(0));
    Ap(6) <= (A(6) and not(S(2)) and not(S(1))) or (A(6) and not(S(0))) or (S(2) and not(S(1)) and S(0));
    Ap(7) <= (A(7) and not(S(2)) and not(S(1))) or (A(7) and not(S(0))) or (S(2) and not(S(1)) and S(0));

	-- Bp = BS2’S1’S0’ + B’S2’S1’S0 + BS1S0 + S2S1’S0’ + BS2S0
	Bp(0) <= ((B(0) and not(S(2)) and not(S(1)) and not(S(0))) or (not(B(0)) and not(S(2)) and not(S(1)) and S(0)) or (B(0) and S(1) and S(0)) or (S(2) and not(S(1)) and not(S(0))) or (B(0) and S(2) and S(0)));
	Bp(1) <= ((B(1) and not(S(2)) and not(S(1)) and not(S(0))) or (not(B(1)) and not(S(2)) and not(S(1)) and S(0)) or (B(1) and S(1) and S(0)) or (S(2) and not(S(1)) and not(S(0))) or (B(1) and S(2) and S(0)));
	Bp(2) <= ((B(2) and not(S(2)) and not(S(1)) and not(S(0))) or (not(B(2)) and not(S(2)) and not(S(1)) and S(0)) or (B(2) and S(1) and S(0)) or (S(2) and not(S(1)) and not(S(0))) or (B(2) and S(2) and S(0)));
	Bp(3) <= ((B(3) and not(S(2)) and not(S(1)) and not(S(0))) or (not(B(3)) and not(S(2)) and not(S(1)) and S(0)) or (B(3) and S(1) and S(0)) or (S(2) and not(S(1)) and not(S(0))) or (B(3) and S(2) and S(0)));
	Bp(4) <= ((B(4) and not(S(2)) and not(S(1)) and not(S(0))) or (not(B(4)) and not(S(2)) and not(S(1)) and S(0)) or (B(4) and S(1) and S(0)) or (S(2) and not(S(1)) and not(S(0))) or (B(4) and S(2) and S(0)));
	Bp(5) <= ((B(5) and not(S(2)) and not(S(1)) and not(S(0))) or (not(B(5)) and not(S(2)) and not(S(1)) and S(0)) or (B(5) and S(1) and S(0)) or (S(2) and not(S(1)) and not(S(0))) or (B(5) and S(2) and S(0)));
	Bp(6) <= ((B(6) and not(S(2)) and not(S(1)) and not(S(0))) or (not(B(6)) and not(S(2)) and not(S(1)) and S(0)) or (B(6) and S(1) and S(0)) or (S(2) and not(S(1)) and not(S(0))) or (B(6) and S(2) and S(0)));
	Bp(7) <= ((B(7) and not(S(2)) and not(S(1)) and not(S(0))) or (not(B(7)) and not(S(2)) and not(S(1)) and S(0)) or (B(7) and S(1) and S(0)) or (S(2) and not(S(1)) and not(S(0))) or (B(7) and S(2) and S(0)));

	--S2’S0 + S2’S1
	cin <= (not(S(2)) and S(0)) or (not(S(2)) and S(1));

	Sum1: Sumador8Bits port map (Ap, Bp, cin, R, cout, v);

end arch;

Proyecto/ALU2.0/Unidad_Aritmetica_tb.vhd
library IEEE;
use IEEE.std_logic_1164.all;

entity Unidad_Aritmetica_tb is
end entity Unidad_Aritmetica_tb;

architecture arch of Unidad_Aritmetica_tb is
    component Unidad_Aritmetica
        port (
            A, B: in std_logic_vector(7 downto 0);
            S : in std_logic_vector(2 downto 0);
            R: out std_logic_vector(7 downto 0);
            cout: out std_logic;
            v: out std_logic
        );
    end component;

    signal A_tb: std_logic_vector(7 downto 0);
    signal B_tb: std_logic_vector(7 downto 0);
    signal S_tb: std_logic_vector(2 downto 0);
    signal R_tb: std_logic_vector(7 downto 0);
    signal cout_tb: std_logic;
    signal v_tb: std_logic;

begin
    test: Unidad_Aritmetica port map (A => A_tb, B => B_tb, S => S_tb, R => R_tb, cout => cout_tb, v => v_tb);

    -- Proceso de estímulo
    process
    begin
        -- Valores de entrada de prueba
        A_tb <= "00000001";
        B_tb <= "00000010";
        S_tb <= "000";
        wait for 10 ns;

        -- Valores de entrada de prueba
        A_tb <= "11111111";
        B_tb <= "00001111";
        S_tb <= "001";
        wait for 10 ns;

        -- Valores de entrada de prueba
        A_tb <= "01010101";
        B_tb <= "10101010";
        S_tb <= "010";
        wait for 10 ns;

        -- Valores de entrada de prueba
        A_tb <= "00110011";
        B_tb <= "11001100";
        S_tb <= "011";
        wait for 10 ns;

        -- Valores de entrada de prueba
        A_tb <= "10010011";
        B_tb <= "01001110";
        S_tb <= "100";
        wait for 10 ns;

        -- Valores de entrada de prueba
        A_tb <= "10010011";
        B_tb <= "01001110";
        S_tb <= "101";
        wait for 10 ns;

        -- Valores de entrada de prueba
        A_tb <= "10101010";
        B_tb <= "01010101";
        S_tb <= "110";
        wait for 10 ns;

        -- Valores de entrada de prueba
        A_tb <= "11110000";
        B_tb <= "00001111";
        S_tb <= "111";
        wait for 10 ns;

        wait;
    end process;

end architecture arch;

Proyecto/ALU2.0/Unidad_Aritmetica.vcd
$date
  Tue Jun 20 13:11:57 2023
$end
$version
  GHDL v0
$end
$timescale
  1 fs
$end
$scope module standard $end
$upscope $end
$scope module std_logic_1164 $end
$upscope $end
$scope module unidad_aritmetica_tb $end
$var reg 8 ! a_tb[7:0] $end
$var reg 8 " b_tb[7:0] $end
$var reg 3 # s_tb[2:0] $end
$var reg 8 $ r_tb[7:0] $end
$var reg 1 % cout_tb $end
$var reg 1 & v_tb $end
$scope module test $end
$var reg 8 ' a[7:0] $end
$var reg 8 ( b[7:0] $end
$var reg 3 ) s[2:0] $end
$var reg 8 * r[7:0] $end
$var reg 1 + cout $end
$var reg 1 , v $end
$var reg 8 - ap[7:0] $end
$var reg 8 . bp[7:0] $end
$var reg 1 / cin $end
$scope module sum1 $end
$var reg 8 0 a[7:0] $end
$var reg 8 1 b[7:0] $end
$var reg 1 2 cin $end
$var reg 8 3 r[7:0] $end
$var reg 1 4 cout $end
$var reg 1 5 v $end
$var reg 7 6 c[6:0] $end
$var reg 1 7 w $end
$scope module sumador0 $end
$var reg 1 8 a $end
$var reg 1 9 b $end
$var reg 1 : cin $end
$var reg 1 ; r $end
$var reg 1 < cout $end
$upscope $end
$scope module sumador1 $end
$var reg 1 = a $end
$var reg 1 > b $end
$var reg 1 ? cin $end
$var reg 1 @ r $end
$var reg 1 A cout $end
$upscope $end
$scope module sumador2 $end
$var reg 1 B a $end
$var reg 1 C b $end
$var reg 1 D cin $end
$var reg 1 E r $end
$var reg 1 F cout $end
$upscope $end
$scope module sumador3 $end
$var reg 1 G a $end
$var reg 1 H b $end
$var reg 1 I cin $end
$var reg 1 J r $end
$var reg 1 K cout $end
$upscope $end
$scope module sumador4 $end
$var reg 1 L a $end
$var reg 1 M b $end
$var reg 1 N cin $end
$var reg 1 O r $end
$var reg 1 P cout $end
$upscope $end
$scope module sumador5 $end
$var reg 1 Q a $end
$var reg 1 R b $end
$var reg 1 S cin $end
$var reg 1 T r $end
$var reg 1 U cout $end
$upscope $end
$scope module sumador6 $end
$var reg 1 V a $end
$var reg 1 W b $end
$var reg 1 X cin $end
$var reg 1 Y r $end
$var reg 1 Z cout $end
$upscope $end
$scope module sumador7 $end
$var reg 1 [ a $end
$var reg 1 \ b $end
$var reg 1 ] cin $end
$var reg 1 ^ r $end
$var reg 1 _ cout $end
$upscope $end
$upscope $end
$upscope $end
$upscope $end
$enddefinitions $end
#0
b00000001 !
b00000010 "
b000 #
b00000011 $
0%
0&
b00000001 '
b00000010 (
b000 )
b00000011 *
0+
0,
b00000001 -
b00000010 .
0/
b00000001 0
b00000010 1
02
b00000011 3
04
05
b0000000 6
07
18
09
0:
1;
0<
0=
1>
0?
1@
0A
0B
0C
0D
0E
0F
0G
0H
0I
0J
0K
0L
0M
0N
0O
0P
0Q
0R
0S
0T
0U
0V
0W
0X
0Y
0Z
0[
0\
0]
0^
0_
#10000000
b11111111 !
b00001111 "
b001 #
b11110000 $
1%
b11111111 '
b00001111 (
b001 )
b11110000 *
1+
b11111111 -
b11110000 .
1/
b11111111 0
b11110000 1
12
b11110000 3
14
b1111111 6
17
1:
0;
1<
1=
0>
1?
0@
1A
1B
1D
0E
1F
1G
1I
0J
1K
1L
1M
1N
1O
1P
1Q
1R
1S
1T
1U
1V
1W
1X
1Y
1Z
1[
1\
1]
1^
1_
#20000000
b01010101 !
b10101010 "
b010 #
b01010110 $
0%
0&
b01010101 '
b10101010 (
b010 )
b01010110 *
0+
0,
b01010101 -
b00000000 .
b01010101 0
b00000000 1
b01010110 3
04
05
b0000001 6
07
0=
1@
0A
0D
1E
0F
0G
0I
0J
0K
0M
0N
1O
0P
0Q
0R
0S
0T
0U
0W
0X
1Y
0Z
0[
0\
0]
0^
0_
#30000000
b00110011 !
b11001100 "
b011 #
b11001101 $
b00110011 '
b11001100 (
b011 )
b11001101 *
b00000000 -
b11001100 .
b00000000 0
b11001100 1
b11001101 3
b0000000 6
08
1;
0<
0?
0@
0B
1C
1H
1J
0L
0O
0V
1W
1\
1^
#40000000
b10010011 !
b01001110 "
b100 #
b10010010 $
1%
0&
b10010011 '
b01001110 (
b100 )
b10010010 *
1+
0,
b10010011 -
b11111111 .
0/
b10010011 0
b11111111 1
02
b10010010 3
14
05
b1111111 6
17
18
19
0:
0;
1<
1=
1>
1?
1@
1A
1D
0E
1F
1I
0J
1K
1L
1M
1N
1O
1P
1R
1S
0T
1U
1X
0Y
1Z
1[
1]
1^
1_
#50000000
b101 #
b01001101 $
b101 )
b01001101 *
b11111111 -
b01001110 .
b11111111 0
b01001110 1
b01001101 3
b1111110 6
09
1;
0<
0?
0@
1B
1E
1G
1J
0M
0O
1Q
0R
1V
1Y
0\
0^
#60000000
b10101010 !
b01010101 "
b110 #
b10101010 $
0%
0&
b10101010 '
b01010101 (
b110 )
b10101010 *
0+
0,
b10101010 -
b00000000 .
b10101010 0
b00000000 1
b10101010 3
04
05
b0000000 6
07
08
0;
0>
1@
0A
0B
0C
0D
0E
0F
0H
0I
1J
0K
0L
0N
0O
0P
0S
1T
0U
0V
0W
0X
0Y
0Z
0]
1^
0_
#70000000
b11110000 !
b00001111 "
b111 #
b00001111 $
b11110000 '
b00001111 (
b111 )
b00001111 *
b00000000 -
b00001111 .
b00000000 0
b00001111 1
b00001111 3
19
1;
0=
1>
1C
1E
0G
1H
0Q
0T
0[
0^
